intellisense_xnei/__init__.py
intellisense_xnei/customtkinter_cop.py
intellisense_xnei/tkinter_cop.py
intellisense_xnei-1.0.0.dist-info/METADATA
intellisense_xnei-1.0.0.dist-info/WHEEL
intellisense_xnei-1.0.0.dist-info/top_level.txt
intellisense_xnei-1.0.0.dist-info/RECORD
