Metadata-Version: 2.4
Name: IntelliSense-xnei
Version: 1.0.0
Summary: IntelliSense-xnei is a Python package that provides a large code input window
Home-page: https://github.com/yourusername/IntelliSense-xnei
Author: Hamza Al
Requires-Python: >=3.10
Requires-Dist: tkinter
Requires-Dist: customtkinter
Dynamic: author
Dynamic: home-page
Dynamic: requires-dist
Dynamic: requires-python
Dynamic: summary
